scip_routing/__init__.py
scip_routing/edge_brancher.py
scip_routing/edge_branching_eventhdlr.py
scip_routing/pricing.py
scip_routing/solver.py
scip_routing/utils.py
scip_routing-0.3.0.dist-info/LICENSE
scip_routing-0.3.0.dist-info/METADATA
scip_routing-0.3.0.dist-info/WHEEL
scip_routing-0.3.0.dist-info/top_level.txt
scip_routing-0.3.0.dist-info/RECORD
