Metadata-Version: 2.1
Name: scip-routing
Version: 0.3.0
Summary: An basic VRPTW Branch-and-Price solver
Home-page: https://github.com/mmghannam/scip-routing
Author: Mohammed Ghannam
Author-email: mohammad.m.ghannam@gmail.com
License: MIT License
Platform: UNKNOWN
Requires-Dist: pyscipopt
Requires-Dist: networkx
Requires-Dist: maturin
